gitcd/__init__.py
gitcd/cli_interface.py
gitcd/gitcd.py
git_cd-0.0.1.dist-info/LICENSE
git_cd-0.0.1.dist-info/METADATA
git_cd-0.0.1.dist-info/WHEEL
git_cd-0.0.1.dist-info/entry_points.txt
git_cd-0.0.1.dist-info/top_level.txt
git_cd-0.0.1.dist-info/RECORD
