Metadata-Version: 2.1
Name: git-cd
Version: 0.0.1
Summary: A terminal tool for easy navigation to local git repository
Home-page: https://github.com/Doma1204/git-cd
Author: Joseph Lam
Author-email: mhlamaf@connect.ust.hk
License: MIT
Keywords: git terminal
Platform: UNKNOWN
Classifier: Development Status :: 3 - Alpha
Classifier: Natural Language :: English
Classifier: License :: OSI Approved :: MIT License
Classifier: Programming Language :: Python :: 2.7
Classifier: Programming Language :: Python :: 3
Classifier: Programming Language :: Python :: 3.5
Classifier: Programming Language :: Python :: 3.6
Classifier: Programming Language :: Python :: 3.7
Requires-Dist: Click
